{"changelog.md":"DFVJvgyJ","contact.md":"DCf4HM83","donate.md":"B4N2IKue","guide_index.md":"BRiBcEAw","guide_milestones.md":"DR_0dtfI","guide_operation.md":"OkLEItI3","guide_preferences.md":"CdkXkbt0","guide_started.md":"CmpiTQKh","guide_window-arrangement.md":"DJbllQW8","help_escrcpy.md":"CDBN-B9Q","help_index.md":"DMrcO1sT","help_scrcpy.md":"CBLhCR8a","index.md":"Ddw6z3uV","reference_gnirehtet_api.md":"C_zu9_fD","reference_gnirehtet_index.md":"C6P1MihC","reference_index.md":"CAnRoDiI","reference_scrcpy_audio.md":"DM9gKuj5","reference_scrcpy_build.md":"DD06e27n","reference_scrcpy_camera.md":"B2WF3K9R","reference_scrcpy_connection.md":"Cjr0io3-","reference_scrcpy_control.md":"CbHytRzy","reference_scrcpy_develop.md":"Sl3wpR0v","reference_scrcpy_device.md":"DE-W9T4t","reference_scrcpy_gamepad.md":"NdGAIR3Y","reference_scrcpy_index.md":"fWyt06H2","reference_scrcpy_keyboard.md":"DW2FkkOK","reference_scrcpy_linux.md":"DQxpCim9","reference_scrcpy_macos.md":"ChLdm_Mn","reference_scrcpy_mouse.md":"ClWULCb6","reference_scrcpy_otg.md":"E8he96Yw","reference_scrcpy_recording.md":"vzzT3aDn","reference_scrcpy_shortcuts.md":"ajAmW25Q","reference_scrcpy_tunnels.md":"BDvYFZ8L","reference_scrcpy_v4l2.md":"CkHYJLVg","reference_scrcpy_video.md":"kq_m8NSf","reference_scrcpy_virtual_display.md":"D20bviJq","reference_scrcpy_window.md":"CtPJxXaV","reference_scrcpy_windows.md":"Ch-244VH","zhhans_changelog.md":"C_qbE7D8","zhhans_contact.md":"COLt2TaV","zhhans_donate.md":"Da3vfvnF","zhhans_guide_index.md":"D2MrTL0s","zhhans_guide_milestones.md":"BG3SHAmR","zhhans_guide_operation.md":"D_glg1t_","zhhans_guide_preferences.md":"CtRhdoX0","zhhans_guide_started.md":"O3YlSval","zhhans_guide_window-arrangement.md":"Dy0FBq_o","zhhans_help_escrcpy.md":"CHb-1BCc","zhhans_help_index.md":"Cea7fvO_","zhhans_help_scrcpy.md":"CT8UTnJA","zhhans_index.md":"ClT1xl5Y","zhhans_reference_gnirehtet_api.md":"DQyl5p5D","zhhans_reference_gnirehtet_index.md":"DnyD05Td","zhhans_reference_index.md":"CeLCx8AA","zhhans_reference_scrcpy_audio.md":"DoM0vV-b","zhhans_reference_scrcpy_build.md":"BD2u15Lt","zhhans_reference_scrcpy_camera.md":"CfzvZ2M0","zhhans_reference_scrcpy_connection.md":"Du3q-q5n","zhhans_reference_scrcpy_control.md":"BfFAS7GQ","zhhans_reference_scrcpy_develop.md":"Bg_Z0rvv","zhhans_reference_scrcpy_device.md":"CQ4sSjlM","zhhans_reference_scrcpy_gamepad.md":"DKIXp63q","zhhans_reference_scrcpy_index.md":"BQm_AdIB","zhhans_reference_scrcpy_keyboard.md":"DDrKqAjs","zhhans_reference_scrcpy_linux.md":"D0zPpLQl","zhhans_reference_scrcpy_macos.md":"tciOCeNP","zhhans_reference_scrcpy_mouse.md":"KJqdoTnv","zhhans_reference_scrcpy_otg.md":"cdHhGVdM","zhhans_reference_scrcpy_recording.md":"-1hFKeHG","zhhans_reference_scrcpy_shortcuts.md":"CgyfUs4d","zhhans_reference_scrcpy_tunnels.md":"BRNxOdhd","zhhans_reference_scrcpy_v4l2.md":"D02X1bg2","zhhans_reference_scrcpy_video.md":"BIjqBxW4","zhhans_reference_scrcpy_virtual_display.md":"DzpP7SMq","zhhans_reference_scrcpy_window.md":"CryCLWVQ","zhhans_reference_scrcpy_windows.md":"CSYbzooE"}
