{"changelog.md":"FfkC5KKe","contact.md":"DedciCVO","donate.md":"C_TIca0k","guide_index.md":"BkGrc1KS","guide_milestones.md":"BT2l6dQZ","guide_operation.md":"CRtR88SG","guide_preferences.md":"CWaPTh4Q","guide_started.md":"CcNvz2xm","guide_window-arrangement.md":"DVTvhkiz","help_escrcpy.md":"BmX9_GLx","help_index.md":"2NRcAaeV","help_scrcpy.md":"1xYi7gHb","index.md":"yO2yS44E","reference_gnirehtet_api.md":"DTTt0pO9","reference_gnirehtet_index.md":"xWLdeqvw","reference_index.md":"ByGZRX0h","reference_scrcpy_audio.md":"B_ErbhzQ","reference_scrcpy_build.md":"DSMjpGt-","reference_scrcpy_camera.md":"OIv-4pcS","reference_scrcpy_connection.md":"3tFLKxe0","reference_scrcpy_control.md":"C0OIneN3","reference_scrcpy_develop.md":"BT4CnVtb","reference_scrcpy_device.md":"DtkmEX0I","reference_scrcpy_gamepad.md":"55TZJh3I","reference_scrcpy_index.md":"XUGuTEi_","reference_scrcpy_keyboard.md":"CfjQjY-s","reference_scrcpy_linux.md":"DGHvabUg","reference_scrcpy_macos.md":"DB6wW-dn","reference_scrcpy_mouse.md":"BPkjww3H","reference_scrcpy_otg.md":"wXN8c7Z_","reference_scrcpy_recording.md":"Doro7pVZ","reference_scrcpy_shortcuts.md":"BbeIeiHc","reference_scrcpy_tunnels.md":"DH6H6Zh7","reference_scrcpy_v4l2.md":"CU4FUCBo","reference_scrcpy_video.md":"CKYjJoWW","reference_scrcpy_virtual_display.md":"DYDkZwO7","reference_scrcpy_window.md":"CnoFWrqh","reference_scrcpy_windows.md":"CPUgbydB","zhhans_changelog.md":"C7-0OJl9","zhhans_contact.md":"YBvCzz9k","zhhans_donate.md":"B3kFBToS","zhhans_guide_index.md":"B0PzraXN","zhhans_guide_milestones.md":"CrsAEspW","zhhans_guide_operation.md":"DrN64X78","zhhans_guide_preferences.md":"MDh_DUbY","zhhans_guide_started.md":"C348Z88k","zhhans_guide_window-arrangement.md":"xsR76FoE","zhhans_help_escrcpy.md":"DUC91eEQ","zhhans_help_index.md":"NXQpTE51","zhhans_help_scrcpy.md":"BFyV_YOU","zhhans_index.md":"QnuiEnub","zhhans_reference_gnirehtet_api.md":"DbJtTAaB","zhhans_reference_gnirehtet_index.md":"jaxFf3DR","zhhans_reference_index.md":"0cudQZsD","zhhans_reference_scrcpy_audio.md":"Ij1Pl08r","zhhans_reference_scrcpy_build.md":"CwyPGSxB","zhhans_reference_scrcpy_camera.md":"B9XrRapO","zhhans_reference_scrcpy_connection.md":"CK4xU0n0","zhhans_reference_scrcpy_control.md":"ClwVIcb0","zhhans_reference_scrcpy_develop.md":"DaBb6iFB","zhhans_reference_scrcpy_device.md":"B_VKAZeR","zhhans_reference_scrcpy_gamepad.md":"D-cXW4Ho","zhhans_reference_scrcpy_index.md":"lXFtFBb8","zhhans_reference_scrcpy_keyboard.md":"EmOLdQs3","zhhans_reference_scrcpy_linux.md":"DQQYPPi6","zhhans_reference_scrcpy_macos.md":"CiGvHBmD","zhhans_reference_scrcpy_mouse.md":"Dk9xC32t","zhhans_reference_scrcpy_otg.md":"CQkQP16i","zhhans_reference_scrcpy_recording.md":"B8aBuHvw","zhhans_reference_scrcpy_shortcuts.md":"D_D3_IPA","zhhans_reference_scrcpy_tunnels.md":"C9UhEb7P","zhhans_reference_scrcpy_v4l2.md":"BfDfjEey","zhhans_reference_scrcpy_video.md":"_va3Mphz","zhhans_reference_scrcpy_virtual_display.md":"hgLXx6Pn","zhhans_reference_scrcpy_window.md":"Bx3G0PRc","zhhans_reference_scrcpy_windows.md":"CMLUBYJf"}
