{"changelog.md":"B1MAOwY3","contact.md":"C1graRe3","donate.md":"BgxiO_Tp","guide_index.md":"Ck35QkDW","guide_milestones.md":"BhPBONVs","guide_operation.md":"DuS5owe7","guide_preferences.md":"CaV7NK7O","guide_started.md":"Cj4q9qM3","guide_window-arrangement.md":"tDVaf179","help_escrcpy.md":"Cnyg98ZK","help_index.md":"3HVCPmF9","help_scrcpy.md":"C-LZHyl0","index.md":"Ca39U5gu","reference_gnirehtet_api.md":"B3tfEg-T","reference_gnirehtet_index.md":"BPA1hCYR","reference_index.md":"CY8V73gA","reference_scrcpy_audio.md":"DuyVIlY8","reference_scrcpy_build.md":"Bt0pTCK2","reference_scrcpy_camera.md":"Bl-VNyMD","reference_scrcpy_connection.md":"DNFVgvhI","reference_scrcpy_control.md":"DXMaGhEr","reference_scrcpy_develop.md":"C7OlVqa2","reference_scrcpy_device.md":"DCUAOv23","reference_scrcpy_gamepad.md":"OjAEJ1UJ","reference_scrcpy_index.md":"DPaZc1ui","reference_scrcpy_keyboard.md":"AxIjpZdZ","reference_scrcpy_linux.md":"Ka74TNIX","reference_scrcpy_macos.md":"B8mltw3g","reference_scrcpy_mouse.md":"BxjGY9LN","reference_scrcpy_otg.md":"C_3tZ9hL","reference_scrcpy_recording.md":"DBwS1A-g","reference_scrcpy_shortcuts.md":"BX86XvBP","reference_scrcpy_tunnels.md":"CtSXMQ6v","reference_scrcpy_v4l2.md":"DxyIGzvQ","reference_scrcpy_video.md":"D92jzuh2","reference_scrcpy_virtual_display.md":"CtJnTFlu","reference_scrcpy_window.md":"BRAWExBi","reference_scrcpy_windows.md":"bsydOG8q","zhhans_changelog.md":"DupC29eS","zhhans_contact.md":"DrJehxYc","zhhans_donate.md":"UBx8cTjG","zhhans_guide_index.md":"CIiVWgnZ","zhhans_guide_milestones.md":"8VHDHEEe","zhhans_guide_operation.md":"IKa4EJQG","zhhans_guide_preferences.md":"CxG_AdFy","zhhans_guide_started.md":"bHd2xKfh","zhhans_guide_window-arrangement.md":"B-NEaiOx","zhhans_help_escrcpy.md":"DVG_u1lU","zhhans_help_index.md":"VDkPsbNB","zhhans_help_scrcpy.md":"_9ELZ3e8","zhhans_index.md":"BnbnEcLD","zhhans_reference_gnirehtet_api.md":"CgCER7sx","zhhans_reference_gnirehtet_index.md":"3wUjzXiG","zhhans_reference_index.md":"CWNVqw5p","zhhans_reference_scrcpy_audio.md":"DzhgnVTA","zhhans_reference_scrcpy_build.md":"DOosdS3x","zhhans_reference_scrcpy_camera.md":"BgeKYK93","zhhans_reference_scrcpy_connection.md":"CAq7Ea_n","zhhans_reference_scrcpy_control.md":"w6bIEBxs","zhhans_reference_scrcpy_develop.md":"CKJKRgp2","zhhans_reference_scrcpy_device.md":"DpbUBktT","zhhans_reference_scrcpy_gamepad.md":"CU1N0_pU","zhhans_reference_scrcpy_index.md":"ydQAxyTZ","zhhans_reference_scrcpy_keyboard.md":"C7dG5_qK","zhhans_reference_scrcpy_linux.md":"DPGOMwDt","zhhans_reference_scrcpy_macos.md":"C0ROH-W_","zhhans_reference_scrcpy_mouse.md":"W_CSu-Me","zhhans_reference_scrcpy_otg.md":"DSbQT-2c","zhhans_reference_scrcpy_recording.md":"CqmbQI5O","zhhans_reference_scrcpy_shortcuts.md":"sRZgd4YB","zhhans_reference_scrcpy_tunnels.md":"V8AqiLcn","zhhans_reference_scrcpy_v4l2.md":"BPDb6BmS","zhhans_reference_scrcpy_video.md":"Cufa6zeM","zhhans_reference_scrcpy_virtual_display.md":"Dl_hXb1Q","zhhans_reference_scrcpy_window.md":"CArlkRI3","zhhans_reference_scrcpy_windows.md":"CNw7Lk3E"}
